perlin_cupy/__init__.py
perlin_cupy/interpolant.py
perlin_cupy/perlin2d.py
perlin_cupy/perlin3d.py
perlin_cupy-0.0.3.dist-info/LICENSE
perlin_cupy-0.0.3.dist-info/METADATA
perlin_cupy-0.0.3.dist-info/WHEEL
perlin_cupy-0.0.3.dist-info/top_level.txt
perlin_cupy-0.0.3.dist-info/RECORD
