Metadata-Version: 2.1
Name: perlin-cupy
Version: 0.0.3
Summary: Perlin-NumPy for GPU
Home-page: https://github.com/jpvt/perlin-cupy
Author: jpvt (João Pedro Vasconcelos)
Author-email: joaoteixeira@eng.ci.ufpb.br
License: MIT
Project-URL: Source, https://github.com/jpvt/perlin-cupy
Project-URL: Tracker, https://github.com/jpvt/perlin-cupy/issues
Keywords: python,perlin,noise,gpu
Platform: UNKNOWN
Classifier: Development Status :: 4 - Beta
Classifier: Intended Audience :: Developers
Classifier: Programming Language :: Python :: 3
Classifier: Operating System :: Unix
Classifier: License :: OSI Approved :: MIT License
